curation/__init__.py
curation/base.py
curation/fields.py
curation/generic.py
curation/models.py
curation/urls.py
curation/widgets.py
curation/migrations/0001_initial.py
curation/migrations/__init__.py
curation/static/curation/curated_related_generic.js
curation/static/curation/curation.css
curation/static/curation/curation.js
curation/static/curation/img/icon-related-lookup-hover.png
curation/static/curation/img/icon-related-lookup.png
curation/views/__init__.py
curation/views/contenttypes.py
django_curation-2.1.0.dist-info/licenses/LICENSE
django_curation-2.1.0.dist-info/METADATA
django_curation-2.1.0.dist-info/WHEEL
django_curation-2.1.0.dist-info/top_level.txt
django_curation-2.1.0.dist-info/RECORD
